Metadata-Version: 2.1
Name: juham
Version: 0.1.5
Summary: Juha's Ultimate Home Automation Masterpiece
Author-email: J Meskanen <juham.api@gmail.com>
Maintainer-email: "J. Meskanen" <juham.api@gmail.com>
License: LICENSE
Project-URL: Homepage, https://meskanen.com
Project-URL: Bug Reports, https://meskanen.com
Project-URL: Funding, https://meskanen.com
Project-URL: Say Thanks!, http://meskanen.com
Project-URL: Source, https://meskanen.com
Keywords: home,automation,juham
Classifier: Development Status :: 2 - Pre-Alpha
Classifier: Intended Audience :: Developers
Classifier: Topic :: Software Development
Classifier: License :: Public Domain
Classifier: Programming Language :: Python :: 3.8
Requires-Python: >=3.8
License-File: LICENSE.rst
Requires-Dist: masterpiece>=0.1.7
Requires-Dist: masterpiece_influx>=0.0.2
Requires-Dist: masterpiece_pahomqtt>=0.0.3
Requires-Dist: requests>=2.31
Requires-Dist: pytz>=2024.1
Requires-Dist: importlib-metadata
Provides-Extra: dev
Requires-Dist: check-manifest; extra == "dev"
